kashasa/__init__.py
kashasa/base.py
kashasa/compat.py
kashasa/native.py
kashasa-0.0.3.dist-info/METADATA
kashasa-0.0.3.dist-info/WHEEL
kashasa-0.0.3.dist-info/top_level.txt
kashasa-0.0.3.dist-info/RECORD
